{
  "Storage unit 1": {
    "Discharging power (MW)": {
      "time period 1": 0.0,
      "time period 2": 0.0,
      "time period 3": 0.0,
      "time period 4": 0.0,
      "time period 5": 0.0,
      "time period 6": 0.0,
      "time period 7": 233.99999999999997,
      "time period 8": 0.0,
      "time period 9": 0.0,
      "time period 10": 0.0,
      "time period 11": 0.0,
      "time period 12": 300.0,
      "time period 13": 0.0,
      "time period 14": 0.0,
      "time period 15": 300.0,
      "time period 16": 300.0,
      "time period 17": 0.0,
      "time period 18": 0.0,
      "time period 19": 0.0,
      "time period 20": 300.0,
      "time period 21": 300.0,
      "time period 22": 0.0,
      "time period 23": 0.0,
      "time period 24": 0.0,
      "time period 25": 0.0,
      "time period 26": 0.0,
      "time period 27": 0.0,
      "time period 28": 2.0000000000001137,
      "time period 29": 300.0,
      "time period 30": 300.0,
      "time period 31": 300.0,
      "time period 32": 0.0,
      "time period 33": 0.0,
      "time period 34": 0.0,
      "time period 35": 0.0,
      "time period 36": 300.0,
      "time period 37": 0.0,
      "time period 38": 0.0,
      "time period 39": 300.0,
      "time period 40": 0.0,
      "time period 41": 300.0,
      "time period 42": 0.0
    },
    "Charging power (MW)": {
      "time period 1": 300.0,
      "time period 2": 0.0,
      "time period 3": 0.0,
      "time period 4": 0.0,
      "time period 5": 0.0,
      "time period 6": 0.0,
      "time period 7": 0.0,
      "time period 8": 0.0,
      "time period 9": 0.0,
      "time period 10": 300.0,
      "time period 11": 0.0,
      "time period 12": 0.0,
      "time period 13": 0.0,
      "time period 14": 300.0,
      "time period 15": 0.0,
      "time period 16": 0.0,
      "time period 17": 300.0,
      "time period 18": 300.0,
      "time period 19": 0.0,
      "time period 20": 0.0,
      "time period 21": 0.0,
      "time period 22": 0.0,
      "time period 23": 300.0,
      "time period 24": 300.0,
      "time period 25": 300.0,
      "time period 26": 300.0,
      "time period 27": 0.0,
      "time period 28": 0.0,
      "time period 29": 0.0,
      "time period 30": 0.0,
      "time period 31": 0.0,
      "time period 32": 300.0,
      "time period 33": 300.0,
      "time period 34": 0.0,
      "time period 35": 0.0,
      "time period 36": 0.0,
      "time period 37": 300.0,
      "time period 38": 300.0,
      "time period 39": 0.0,
      "time period 40": 0.0,
      "time period 41": 0.0,
      "time period 42": 0.0
    },
    "Net discharging power (MW)": {
      "time period 1": -300.0,
      "time period 2": 0.0,
      "time period 3": 0.0,
      "time period 4": 0.0,
      "time period 5": 0.0,
      "time period 6": 0.0,
      "time period 7": 233.99999999999997,
      "time period 8": 0.0,
      "time period 9": 0.0,
      "time period 10": -300.0,
      "time period 11": 0.0,
      "time period 12": 300.0,
      "time period 13": 0.0,
      "time period 14": -300.0,
      "time period 15": 300.0,
      "time period 16": 300.0,
      "time period 17": -300.0,
      "time period 18": -300.0,
      "time period 19": 0.0,
      "time period 20": 300.0,
      "time period 21": 300.0,
      "time period 22": 0.0,
      "time period 23": -300.0,
      "time period 24": -300.0,
      "time period 25": -300.0,
      "time period 26": -300.0,
      "time period 27": 0.0,
      "time period 28": 2.0000000000001137,
      "time period 29": 300.0,
      "time period 30": 300.0,
      "time period 31": 300.0,
      "time period 32": -300.0,
      "time period 33": -300.0,
      "time period 34": 0.0,
      "time period 35": 0.0,
      "time period 36": 300.0,
      "time period 37": -300.0,
      "time period 38": -300.0,
      "time period 39": 300.0,
      "time period 40": 0.0,
      "time period 41": 300.0,
      "time period 42": 0.0
    },
    "Stored energy (MWh)": {
      "time period 1": 550.0,
      "time period 2": 550.0,
      "time period 3": 550.0,
      "time period 4": 550.0,
      "time period 5": 550.0,
      "time period 6": 550.0,
      "time period 7": 412.3529411764706,
      "time period 8": 412.3529411764706,
      "time period 9": 412.3529411764706,
      "time period 10": 539.8529411764706,
      "time period 11": 539.8529411764706,
      "time period 12": 363.38235294117646,
      "time period 13": 363.38235294117646,
      "time period 14": 490.88235294117646,
      "time period 15": 314.4117647058823,
      "time period 16": 137.94117647058823,
      "time period 17": 265.44117647058823,
      "time period 18": 392.94117647058823,
      "time period 19": 392.94117647058823,
      "time period 20": 216.47058823529412,
      "time period 21": 40.0,
      "time period 22": 40.0,
      "time period 23": 167.5,
      "time period 24": 295.0,
      "time period 25": 422.5,
      "time period 26": 550.0,
      "time period 27": 550.0,
      "time period 28": 548.8235294117646,
      "time period 29": 372.35294117647055,
      "time period 30": 195.88235294117644,
      "time period 31": 19.41176470588232,
      "time period 32": 146.91176470588232,
      "time period 33": 274.4117647058823,
      "time period 34": 274.4117647058823,
      "time period 35": 274.4117647058823,
      "time period 36": 97.94117647058823,
      "time period 37": 225.44117647058823,
      "time period 38": 352.94117647058823,
      "time period 39": 176.47058823529412,
      "time period 40": 176.47058823529412,
      "time period 41": 0.0,
      "time period 42": 0.0
    },
    "Final energy (MWh)": 0.0,
    "Hourly average cost ($)": {
      "time period 1": 30301.4169228431,
      "time period 2": 0.0,
      "time period 3": 0.0,
      "time period 4": 0.0,
      "time period 5": 0.0,
      "time period 6": 0.0,
      "time period 7": 0.0,
      "time period 8": 0.0,
      "time period 9": 0.0,
      "time period 10": 38255.87531243317,
      "time period 11": 0.0,
      "time period 12": 0.0,
      "time period 13": 0.0,
      "time period 14": 45624.82401145935,
      "time period 15": 0.0,
      "time period 16": 0.0,
      "time period 17": 37941.364880218505,
      "time period 18": 48955.96929611207,
      "time period 19": 0.0,
      "time period 20": 0.0,
      "time period 21": 0.0,
      "time period 22": 0.0,
      "time period 23": 36599.267740859985,
      "time period 24": 40480.295582427985,
      "time period 25": 44305.57963623045,
      "time period 26": 46682.12775672915,
      "time period 27": 0.0,
      "time period 28": 0.0,
      "time period 29": 0.0,
      "time period 30": 0.0,
      "time period 31": 0.0,
      "time period 32": 49891.92785634041,
      "time period 33": 51163.89264930722,
      "time period 34": 0.0,
      "time period 35": 0.0,
      "time period 36": 0.0,
      "time period 37": 41614.54992736815,
      "time period 38": 42181.79432167052,
      "time period 39": 0.0,
      "time period 40": 0.0,
      "time period 41": 0.0,
      "time period 42": 0.0
    },
    "Hourly average revenue ($)": {
      "time period 1": 0.0,
      "time period 2": 0.0,
      "time period 3": 0.0,
      "time period 4": 0.0,
      "time period 5": 0.0,
      "time period 6": 0.0,
      "time period 7": 59278.36347598624,
      "time period 8": 0.0,
      "time period 9": 0.0,
      "time period 10": 0.0,
      "time period 11": 0.0,
      "time period 12": 78221.11947308532,
      "time period 13": 0.0,
      "time period 14": 0.0,
      "time period 15": 82255.59510292052,
      "time period 16": 84617.24246086123,
      "time period 17": 0.0,
      "time period 18": 0.0,
      "time period 19": 0.0,
      "time period 20": 82040.76520980836,
      "time period 21": 83957.1095777893,
      "time period 22": 0.0,
      "time period 23": 0.0,
      "time period 24": 0.0,
      "time period 25": 0.0,
      "time period 26": 0.0,
      "time period 27": 0.0,
      "time period 28": 537.7008748413392,
      "time period 29": 92206.04904164317,
      "time period 30": 98122.87327374457,
      "time period 31": 84389.12558163646,
      "time period 32": 0.0,
      "time period 33": 0.0,
      "time period 34": 0.0,
      "time period 35": 0.0,
      "time period 36": 91198.96748794559,
      "time period 37": 0.0,
      "time period 38": 0.0,
      "time period 39": 90429.23436893462,
      "time period 40": 0.0,
      "time period 41": 84365.44117607117,
      "time period 42": 0.0
    },
    "Total average cost ($)": 553998.8858940001,
    "Total average revenue ($)": 1.011619587105268e6,
    "Total average profit ($)": 457620.70121126797
  }
}
