{
  "Storage unit 1": {
    "Discharging power (MW)": {
      "time period 1": 0.0,
      "time period 2": 0.0,
      "time period 3": 0.0,
      "time period 4": 0.0,
      "time period 5": 0.0,
      "time period 6": 0.0,
      "time period 7": 0.0,
      "time period 8": 0.0,
      "time period 9": 0.0,
      "time period 10": 0.0,
      "time period 11": 0.0,
      "time period 12": 0.0,
      "time period 13": 0.0,
      "time period 14": 0.0,
      "time period 15": 0.0,
      "time period 16": 165.0,
      "time period 17": 0.0,
      "time period 18": 300.0,
      "time period 19": 0.0,
      "time period 20": 0.0,
      "time period 21": 0.0,
      "time period 22": 0.0,
      "time period 23": 0.0,
      "time period 24": 0.0,
      "time period 25": 300.0,
      "time period 26": 0.0,
      "time period 27": 0.0
    },
    "Charging power (MW)": {
      "time period 1": 0.0,
      "time period 2": 115.22491349480963,
      "time period 3": 300.0,
      "time period 4": 0.0,
      "time period 5": 300.0,
      "time period 6": 300.0,
      "time period 7": 0.0,
      "time period 8": 0.0,
      "time period 9": 0.0,
      "time period 10": 0.0,
      "time period 11": 0.0,
      "time period 12": 0.0,
      "time period 13": 0.0,
      "time period 14": 0.0,
      "time period 15": 0.0,
      "time period 16": 0.0,
      "time period 17": 0.0,
      "time period 18": 0.0,
      "time period 19": 0.0,
      "time period 20": 0.0,
      "time period 21": 0.0,
      "time period 22": 0.0,
      "time period 23": 0.0,
      "time period 24": 0.0,
      "time period 25": 0.0,
      "time period 26": 0.0,
      "time period 27": 0.0
    },
    "Net discharging power (MW)": {
      "time period 1": 0.0,
      "time period 2": -115.22491349480963,
      "time period 3": -300.0,
      "time period 4": 0.0,
      "time period 5": -300.0,
      "time period 6": -300.0,
      "time period 7": 0.0,
      "time period 8": 0.0,
      "time period 9": 0.0,
      "time period 10": 0.0,
      "time period 11": 0.0,
      "time period 12": 0.0,
      "time period 13": 0.0,
      "time period 14": 0.0,
      "time period 15": 0.0,
      "time period 16": 165.0,
      "time period 17": 0.0,
      "time period 18": 300.0,
      "time period 19": 0.0,
      "time period 20": 0.0,
      "time period 21": 0.0,
      "time period 22": 0.0,
      "time period 23": 0.0,
      "time period 24": 0.0,
      "time period 25": 300.0,
      "time period 26": 0.0,
      "time period 27": 0.0
    },
    "Stored energy (MWh)": {
      "time period 1": 18.529411764705912,
      "time period 2": 67.5,
      "time period 3": 195.0,
      "time period 4": 195.0,
      "time period 5": 322.5,
      "time period 6": 450.0,
      "time period 7": 450.0,
      "time period 8": 450.0,
      "time period 9": 450.0,
      "time period 10": 450.0,
      "time period 11": 450.0,
      "time period 12": 450.0,
      "time period 13": 450.0,
      "time period 14": 450.0,
      "time period 15": 450.0,
      "time period 16": 352.94117647058823,
      "time period 17": 352.94117647058823,
      "time period 18": 176.47058823529412,
      "time period 19": 176.47058823529412,
      "time period 20": 176.47058823529412,
      "time period 21": 176.47058823529412,
      "time period 22": 176.47058823529412,
      "time period 23": 176.47058823529412,
      "time period 24": 176.47058823529412,
      "time period 25": 0.0,
      "time period 26": 0.0,
      "time period 27": 0.0
    },
    "Final energy (MWh)": 0.0,
    "Hourly average cost ($)": {
      "time period 1": 0.0,
      "time period 2": 18204.365337282852,
      "time period 3": 46240.58093297141,
      "time period 4": 0.0,
      "time period 5": 19540.165198192524,
      "time period 6": 17178.37058125488,
      "time period 7": 0.0,
      "time period 8": 0.0,
      "time period 9": 0.0,
      "time period 10": 0.0,
      "time period 11": 0.0,
      "time period 12": 0.0,
      "time period 13": 0.0,
      "time period 14": 0.0,
      "time period 15": 0.0,
      "time period 16": 0.0,
      "time period 17": 0.0,
      "time period 18": 0.0,
      "time period 19": 0.0,
      "time period 20": 0.0,
      "time period 21": 0.0,
      "time period 22": 0.0,
      "time period 23": 0.0,
      "time period 24": 0.0,
      "time period 25": 0.0,
      "time period 26": 0.0,
      "time period 27": 0.0
    },
    "Hourly average revenue ($)": {
      "time period 1": 0.0,
      "time period 2": 0.0,
      "time period 3": 0.0,
      "time period 4": 0.0,
      "time period 5": 0.0,
      "time period 6": 0.0,
      "time period 7": 0.0,
      "time period 8": 0.0,
      "time period 9": 0.0,
      "time period 10": 0.0,
      "time period 11": 0.0,
      "time period 12": 0.0,
      "time period 13": 0.0,
      "time period 14": 0.0,
      "time period 15": 0.0,
      "time period 16": 87622.83335347364,
      "time period 17": 0.0,
      "time period 18": 203851.96929611213,
      "time period 19": 0.0,
      "time period 20": 0.0,
      "time period 21": 0.0,
      "time period 22": 0.0,
      "time period 23": 0.0,
      "time period 24": 0.0,
      "time period 25": 1.0421385796362308e6,
      "time period 26": 0.0,
      "time period 27": 0.0
    },
    "Total average cost ($)": 101163.48204970168,
    "Total average revenue ($)": 1.3336133822858166e6,
    "Total average profit ($)": 1.2324499002361149e6
  }
}
