{
  "Storage unit 1": {
    "Discharging power (MW)": {
      "time period 1": 13.6,
      "time period 2": 0.0,
      "time period 3": 0.0,
      "time period 4": 0.0,
      "time period 5": 0.0,
      "time period 6": 0.0,
      "time period 7": 13.6,
      "time period 8": 0.0,
      "time period 9": 0.0,
      "time period 10": 13.6,
      "time period 11": 0.0,
      "time period 12": 0.0,
      "time period 13": 0.0
    },
    "Charging power (MW)": {
      "time period 1": 0.0,
      "time period 2": 0.0,
      "time period 3": 18.823529411764707,
      "time period 4": 0.0,
      "time period 5": 0.0,
      "time period 6": 0.0,
      "time period 7": 0.0,
      "time period 8": 18.823529411764707,
      "time period 9": 0.0,
      "time period 10": 0.0,
      "time period 11": 0.0,
      "time period 12": 0.0,
      "time period 13": 0.0
    },
    "Net discharging power (MW)": {
      "time period 1": 13.6,
      "time period 2": 0.0,
      "time period 3": -18.823529411764707,
      "time period 4": 0.0,
      "time period 5": 0.0,
      "time period 6": 0.0,
      "time period 7": 13.6,
      "time period 8": -18.823529411764707,
      "time period 9": 0.0,
      "time period 10": 13.6,
      "time period 11": 0.0,
      "time period 12": 0.0,
      "time period 13": 0.0
    },
    "Stored energy (MWh)": {
      "time period 1": 0.0,
      "time period 2": 0.0,
      "time period 3": 8.0,
      "time period 4": 8.0,
      "time period 5": 8.0,
      "time period 6": 8.0,
      "time period 7": 0.0,
      "time period 8": 8.0,
      "time period 9": 8.0,
      "time period 10": 0.0,
      "time period 11": 0.0,
      "time period 12": 0.0,
      "time period 13": 0.0
    },
    "Final energy (MWh)": 0.0,
    "Hourly average cost ($)": {
      "time period 1": 0.0,
      "time period 2": 0.0,
      "time period 3": 2552.3815487354614,
      "time period 4": 0.0,
      "time period 5": 0.0,
      "time period 6": 0.0,
      "time period 7": 0.0,
      "time period 8": 2427.0040277602257,
      "time period 9": 0.0,
      "time period 10": 0.0,
      "time period 11": 0.0,
      "time period 12": 0.0,
      "time period 13": 0.0
    },
    "Hourly average revenue ($)": {
      "time period 1": 4172.000233835554,
      "time period 2": 0.0,
      "time period 3": 0.0,
      "time period 4": 0.0,
      "time period 5": 0.0,
      "time period 6": 0.0,
      "time period 7": 3986.3822191171466,
      "time period 8": 0.0,
      "time period 9": 0.0,
      "time period 10": 4030.082347496971,
      "time period 11": 0.0,
      "time period 12": 0.0,
      "time period 13": 0.0
    },
    "Total average cost ($)": 4979.385576495687,
    "Total average revenue ($)": 12188.464800449672,
    "Total average profit ($)": 7209.079223953985
  }
}
