{
  "Storage unit 1": {
    "Discharging power (MW)": {
      "time period 1": 0.0,
      "time period 2": 0.0,
      "time period 3": 0.0,
      "time period 4": 0.0,
      "time period 5": 0.0,
      "time period 6": 300.0,
      "time period 7": 0.0,
      "time period 8": 0.0,
      "time period 9": 34.999999999999865,
      "time period 10": 0.0,
      "time period 11": 300.0,
      "time period 12": 0.0
    },
    "Charging power (MW)": {
      "time period 1": 0.0,
      "time period 2": 0.0,
      "time period 3": 0.0,
      "time period 4": 0.0,
      "time period 5": 0.0,
      "time period 6": 0.0,
      "time period 7": 0.0,
      "time period 8": 0.0,
      "time period 9": 0.0,
      "time period 10": 0.0,
      "time period 11": 0.0,
      "time period 12": 0.0
    },
    "Net discharging power (MW)": {
      "time period 1": 0.0,
      "time period 2": 0.0,
      "time period 3": 0.0,
      "time period 4": 0.0,
      "time period 5": 0.0,
      "time period 6": 300.0,
      "time period 7": 0.0,
      "time period 8": 0.0,
      "time period 9": 34.999999999999865,
      "time period 10": 0.0,
      "time period 11": 300.0,
      "time period 12": 0.0
    },
    "Stored energy (MWh)": {
      "time period 1": 373.5294117647058,
      "time period 2": 373.5294117647058,
      "time period 3": 373.5294117647058,
      "time period 4": 373.5294117647058,
      "time period 5": 373.5294117647058,
      "time period 6": 197.05882352941168,
      "time period 7": 197.05882352941168,
      "time period 8": 197.05882352941168,
      "time period 9": 176.47058823529412,
      "time period 10": 176.47058823529412,
      "time period 11": 0.0,
      "time period 12": 0.0
    },
    "Final energy (MWh)": 0.0,
    "Hourly average cost ($)": {
      "time period 1": 0.0,
      "time period 2": 0.0,
      "time period 3": 0.0,
      "time period 4": 0.0,
      "time period 5": 0.0,
      "time period 6": 0.0,
      "time period 7": 0.0,
      "time period 8": 0.0,
      "time period 9": 0.0,
      "time period 10": 0.0,
      "time period 11": 0.0,
      "time period 12": 0.0
    },
    "Hourly average revenue ($)": {
      "time period 1": 0.0,
      "time period 2": 0.0,
      "time period 3": 0.0,
      "time period 4": 0.0,
      "time period 5": 0.0,
      "time period 6": 88440.37058125489,
      "time period 7": 0.0,
      "time period 8": 0.0,
      "time period 9": 9988.228731358324,
      "time period 10": 0.0,
      "time period 11": 87293.69055460143,
      "time period 12": 0.0
    },
    "Total average cost ($)": 0.0,
    "Total average revenue ($)": 185722.28986721463,
    "Total average profit ($)": 185722.28986721463
  }
}
