{
  "Storage unit 1": {
    "Discharging power (MW)": {
      "time period 1": 0.0,
      "time period 2": 0.0,
      "time period 3": 0.0,
      "time period 4": 300.0,
      "time period 5": 0.0,
      "time period 6": 0.0,
      "time period 7": 0.0,
      "time period 8": 0.0,
      "time period 9": 216.75,
      "time period 10": 0.0,
      "time period 11": 0.0,
      "time period 12": 295.0,
      "time period 13": 300.0,
      "time period 14": 0.0,
      "time period 15": 0.0,
      "time period 16": 0.0,
      "time period 17": 133.5,
      "time period 18": 300.0,
      "time period 19": 0.0,
      "time period 20": 0.0,
      "time period 21": 0.0,
      "time period 22": 0.0,
      "time period 23": 0.0,
      "time period 24": 0.0,
      "time period 25": 0.0,
      "time period 26": 295.0,
      "time period 27": 300.0,
      "time period 28": 0.0,
      "time period 29": 0.0,
      "time period 30": 0.0,
      "time period 31": 0.0,
      "time period 32": 0.0,
      "time period 33": 300.0,
      "time period 34": 0.0,
      "time period 35": 0.0,
      "time period 36": 300.0,
      "time period 37": 0.0,
      "time period 38": 295.0,
      "time period 39": 0.0
    },
    "Charging power (MW)": {
      "time period 1": 0.0,
      "time period 2": 0.0,
      "time period 3": 0.0,
      "time period 4": 0.0,
      "time period 5": 0.0,
      "time period 6": 0.0,
      "time period 7": 300.0,
      "time period 8": 115.22491349480975,
      "time period 9": 0.0,
      "time period 10": 0.0,
      "time period 11": 300.0,
      "time period 12": 0.0,
      "time period 13": 0.0,
      "time period 14": 300.0,
      "time period 15": 300.0,
      "time period 16": 0.0,
      "time period 17": 0.0,
      "time period 18": 0.0,
      "time period 19": 0.0,
      "time period 20": 300.0,
      "time period 21": 300.0,
      "time period 22": 223.52941176470588,
      "time period 23": 0.0,
      "time period 24": 0.0,
      "time period 25": 0.0,
      "time period 26": 0.0,
      "time period 27": 0.0,
      "time period 28": 0.0,
      "time period 29": 300.0,
      "time period 30": 300.0,
      "time period 31": 38.75432525951563,
      "time period 32": 0.0,
      "time period 33": 0.0,
      "time period 34": 300.0,
      "time period 35": 300.0,
      "time period 36": 0.0,
      "time period 37": 0.0,
      "time period 38": 0.0,
      "time period 39": 0.0
    },
    "Net discharging power (MW)": {
      "time period 1": 0.0,
      "time period 2": 0.0,
      "time period 3": 0.0,
      "time period 4": 300.0,
      "time period 5": 0.0,
      "time period 6": 0.0,
      "time period 7": -300.0,
      "time period 8": -115.22491349480975,
      "time period 9": 216.75,
      "time period 10": 0.0,
      "time period 11": -300.0,
      "time period 12": 295.0,
      "time period 13": 300.0,
      "time period 14": -300.0,
      "time period 15": -300.0,
      "time period 16": 0.0,
      "time period 17": 133.5,
      "time period 18": 300.0,
      "time period 19": 0.0,
      "time period 20": -300.0,
      "time period 21": -300.0,
      "time period 22": -223.52941176470588,
      "time period 23": 0.0,
      "time period 24": 0.0,
      "time period 25": 0.0,
      "time period 26": 295.0,
      "time period 27": 300.0,
      "time period 28": 0.0,
      "time period 29": -300.0,
      "time period 30": -300.0,
      "time period 31": -38.75432525951563,
      "time period 32": 0.0,
      "time period 33": 300.0,
      "time period 34": -300.0,
      "time period 35": -300.0,
      "time period 36": 300.0,
      "time period 37": 0.0,
      "time period 38": 295.0,
      "time period 39": 0.0
    },
    "Stored energy (MWh)": {
      "time period 1": 350.0,
      "time period 2": 350.0,
      "time period 3": 350.0,
      "time period 4": 173.52941176470588,
      "time period 5": 173.52941176470588,
      "time period 6": 173.52941176470588,
      "time period 7": 301.02941176470586,
      "time period 8": 350.0,
      "time period 9": 222.5,
      "time period 10": 222.5,
      "time period 11": 350.0,
      "time period 12": 176.47058823529412,
      "time period 13": 0.0,
      "time period 14": 127.5,
      "time period 15": 255.0,
      "time period 16": 255.0,
      "time period 17": 176.47058823529412,
      "time period 18": 0.0,
      "time period 19": 0.0,
      "time period 20": 127.5,
      "time period 21": 255.0,
      "time period 22": 350.0,
      "time period 23": 350.0,
      "time period 24": 350.0,
      "time period 25": 350.0,
      "time period 26": 176.47058823529412,
      "time period 27": 0.0,
      "time period 28": 0.0,
      "time period 29": 127.5,
      "time period 30": 255.0,
      "time period 31": 271.47058823529414,
      "time period 32": 271.47058823529414,
      "time period 33": 95.0,
      "time period 34": 222.5,
      "time period 35": 350.0,
      "time period 36": 173.52941176470588,
      "time period 37": 173.52941176470588,
      "time period 38": 0.0,
      "time period 39": 0.0
    },
    "Final energy (MWh)": 0.0,
    "Hourly average cost ($)": {
      "time period 1": 0.0,
      "time period 2": 0.0,
      "time period 3": 0.0,
      "time period 4": 0.0,
      "time period 5": 0.0,
      "time period 6": 0.0,
      "time period 7": 32947.90189229004,
      "time period 8": 19595.677553147318,
      "time period 9": 0.0,
      "time period 10": 0.0,
      "time period 11": 46421.69055460145,
      "time period 12": 0.0,
      "time period 13": 0.0,
      "time period 14": 39600.82401145935,
      "time period 15": 49204.59510292054,
      "time period 16": 0.0,
      "time period 17": 0.0,
      "time period 18": 0.0,
      "time period 19": 0.0,
      "time period 20": 35948.765209808356,
      "time period 21": 40004.109577789306,
      "time period 22": 32674.05214160694,
      "time period 23": 0.0,
      "time period 24": 0.0,
      "time period 25": 0.0,
      "time period 26": 0.0,
      "time period 27": 0.0,
      "time period 28": 0.0,
      "time period 29": 49714.049041643164,
      "time period 30": 51448.87327374457,
      "time period 31": 7665.105034767352,
      "time period 32": 0.0,
      "time period 33": 0.0,
      "time period 34": 41186.85095466613,
      "time period 35": 38647.014760866165,
      "time period 36": 0.0,
      "time period 37": 0.0,
      "time period 38": 0.0,
      "time period 39": 0.0
    },
    "Hourly average revenue ($)": {
      "time period 1": 0.0,
      "time period 2": 0.0,
      "time period 3": 0.0,
      "time period 4": 73209.09609757415,
      "time period 5": 0.0,
      "time period 6": 0.0,
      "time period 7": 0.0,
      "time period 8": 0.0,
      "time period 9": 53541.14364348354,
      "time period 10": 0.0,
      "time period 11": 0.0,
      "time period 12": 81823.28414853393,
      "time period 13": 88133.36993087768,
      "time period 14": 0.0,
      "time period 15": 0.0,
      "time period 16": 0.0,
      "time period 17": 36738.02737169722,
      "time period 18": 84682.96929611205,
      "time period 19": 0.0,
      "time period 20": 0.0,
      "time period 21": 0.0,
      "time period 22": 0.0,
      "time period 23": 0.0,
      "time period 24": 0.0,
      "time period 25": 0.0,
      "time period 26": 88602.39229411699,
      "time period 27": 101284.98440803528,
      "time period 28": 0.0,
      "time period 29": 0.0,
      "time period 30": 0.0,
      "time period 31": 0.0,
      "time period 32": 0.0,
      "time period 33": 91087.89264930722,
      "time period 34": 0.0,
      "time period 35": 0.0,
      "time period 36": 86854.96748794556,
      "time period 37": 0.0,
      "time period 38": 83103.26441630935,
      "time period 39": 0.0
    },
    "Total average cost ($)": 485059.50910931075,
    "Total average revenue ($)": 869061.391743993,
    "Total average profit ($)": 384001.8826346823
  }
}
